{
  "kind": "youtubeAnalytics#resultTable",
  "columnHeaders": [
    {
      "name": "video",
      "columnType": "DIMENSION",
      "dataType": "STRING"
    },
    {
      "name": "elapsedVideoTimeRatio",
      "columnType": "DIMENSION",
      "dataType": "FLOAT"
    },
    {
      "name": "audienceWatchRatio",
      "columnType": "METRIC",
      "dataType": "FLOAT"
    },
    {
      "name": "relativeRetentionPerformance",
      "columnType": "METRIC",
      "dataType": "FLOAT"
    }
  ],
  "rows": [
    [
      "eJizsGLUFFw",
      0.01,
      1.0635,
      0.71565
    ],
    [
      "eJizsGLUFFw",
      0.02,
      0.873,
      0.77835
    ],
    [
      "eJizsGLUFFw",
      0.03,
      0.8571,
      0.81915
    ],
    [
      "eJizsGLUFFw",
      0.04,
      0.746,
      0.8317
    ],
    [
      "eJizsGLUFFw",
      0.05,
      0.7619,
      0.8365
    ],
    [
      "eJizsGLUFFw",
      0.06,
      0.8095,
      0.8401
    ],
    [
      "eJizsGLUFFw",
      0.07,
      0.8095,
      0.8398
    ],
    [
      "eJizsGLUFFw",
      0.08,
      0.746,
      0.83159999999999989
    ],
    [
      "eJizsGLUFFw",
      0.09,
      0.66670000000000007,
      0.8183
    ],
    [
      "eJizsGLUFFw",
      0.1,
      0.65079999999999993,
      0.8125
    ],
    [
      "eJizsGLUFFw",
      0.11,
      0.6984,
      0.82545
    ],
    [
      "eJizsGLUFFw",
      0.12,
      0.6984,
      0.853
    ],
    [
      "eJizsGLUFFw",
      0.13,
      0.7302,
      0.88125
    ],
    [
      "eJizsGLUFFw",
      0.14,
      0.7143,
      0.90065
    ],
    [
      "eJizsGLUFFw",
      0.15,
      0.7302,
      0.9092
    ],
    [
      "eJizsGLUFFw",
      0.16,
      0.66670000000000007,
      0.90915
    ],
    [
      "eJizsGLUFFw",
      0.17,
      0.7302,
      0.9052
    ],
    [
      "eJizsGLUFFw",
      0.18,
      0.6825,
      0.90195
    ],
    [
      "eJizsGLUFFw",
      0.19,
      0.7302,
      0.90084999999999993
    ],
    [
      "eJizsGLUFFw",
      0.2,
      0.6825,
      0.90005
    ],
    [
      "eJizsGLUFFw",
      0.21,
      0.6825,
      0.8966
    ],
    [
      "eJizsGLUFFw",
      0.22,
      0.65079999999999993,
      0.889
    ],
    [
      "eJizsGLUFFw",
      0.23,
      0.6984,
      0.8792
    ],
    [
      "eJizsGLUFFw",
      0.24,
      0.619,
      0.8712
    ],
    [
      "eJizsGLUFFw",
      0.25,
      0.6825,
      0.8691
    ],
    [
      "eJizsGLUFFw",
      0.26,
      0.6825,
      0.87505000000000011
    ],
    [
      "eJizsGLUFFw",
      0.27,
      0.7143,
      0.88775
    ],
    [
      "eJizsGLUFFw",
      0.28,
      0.746,
      0.903
    ],
    [
      "eJizsGLUFFw",
      0.29,
      0.7619,
      0.91605
    ],
    [
      "eJizsGLUFFw",
      0.3,
      0.79370000000000007,
      0.92455
    ],
    [
      "eJizsGLUFFw",
      0.31,
      0.79370000000000007,
      0.929
    ],
    [
      "eJizsGLUFFw",
      0.32,
      0.7778,
      0.93145000000000011
    ],
    [
      "eJizsGLUFFw",
      0.33,
      0.7778,
      0.93335
    ],
    [
      "eJizsGLUFFw",
      0.34,
      0.8095,
      0.93485
    ],
    [
      "eJizsGLUFFw",
      0.35,
      0.7619,
      0.93505
    ],
    [
      "eJizsGLUFFw",
      0.36,
      0.8095,
      0.9333
    ],
    [
      "eJizsGLUFFw",
      0.37,
      0.746,
      0.92995
    ],
    [
      "eJizsGLUFFw",
      0.38,
      0.746,
      0.92690000000000006
    ],
    [
      "eJizsGLUFFw",
      0.39,
      0.7302,
      0.92625
    ],
    [
      "eJizsGLUFFw",
      0.4,
      0.7619,
      0.92924999999999991
    ],
    [
      "eJizsGLUFFw",
      0.41,
      0.8095,
      0.9346
    ],
    [
      "eJizsGLUFFw",
      0.42,
      0.7619,
      0.9402
    ],
    [
      "eJizsGLUFFw",
      0.43,
      0.8095,
      0.9447
    ],
    [
      "eJizsGLUFFw",
      0.44,
      0.8254,
      0.9477
    ],
    [
      "eJizsGLUFFw",
      0.45,
      0.8254,
      0.94924999999999993
    ],
    [
      "eJizsGLUFFw",
      0.46,
      0.8254,
      0.94909999999999994
    ],
    [
      "eJizsGLUFFw",
      0.47,
      0.873,
      0.9468
    ],
    [
      "eJizsGLUFFw",
      0.48,
      0.84129999999999994,
      0.94245
    ],
    [
      "eJizsGLUFFw",
      0.49,
      0.8095,
      0.9366
    ],
    [
      "eJizsGLUFFw",
      0.5,
      0.7778,
      0.93009999999999993
    ],
    [
      "eJizsGLUFFw",
      0.51,
      0.79370000000000007,
      0.92435
    ],
    [
      "eJizsGLUFFw",
      0.52,
      0.8254,
      0.91989999999999994
    ],
    [
      "eJizsGLUFFw",
      0.53,
      0.8571,
      0.9156
    ],
    [
      "eJizsGLUFFw",
      0.54,
      0.8254,
      0.91065
    ],
    [
      "eJizsGLUFFw",
      0.55,
      0.7778,
      0.90545000000000009
    ],
    [
      "eJizsGLUFFw",
      0.56,
      0.746,
      0.90084999999999993
    ],
    [
      "eJizsGLUFFw",
      0.57,
      0.8095,
      0.8965
    ],
    [
      "eJizsGLUFFw",
      0.58,
      0.8095,
      0.89225
    ],
    [
      "eJizsGLUFFw",
      0.59,
      0.7619,
      0.88975
    ],
    [
      "eJizsGLUFFw",
      0.6,
      0.7302,
      0.89025
    ],
    [
      "eJizsGLUFFw",
      0.61,
      0.8095,
      0.89215
    ],
    [
      "eJizsGLUFFw",
      0.62,
      0.79370000000000007,
      0.89215
    ],
    [
      "eJizsGLUFFw",
      0.63,
      0.7619,
      0.88789999999999991
    ],
    [
      "eJizsGLUFFw",
      0.64,
      0.7619,
      0.87905
    ],
    [
      "eJizsGLUFFw",
      0.65,
      0.7619,
      0.86555
    ],
    [
      "eJizsGLUFFw",
      0.66,
      0.7619,
      0.84725000000000006
    ],
    [
      "eJizsGLUFFw",
      0.67,
      0.7619,
      0.82335
    ],
    [
      "eJizsGLUFFw",
      0.68,
      0.7143,
      0.7925
    ],
    [
      "eJizsGLUFFw",
      0.69,
      0.6984,
      0.75574999999999992
    ],
    [
      "eJizsGLUFFw",
      0.7,
      0.6984,
      0.71825
    ],
    [
      "eJizsGLUFFw",
      0.71,
      0.6984,
      0.68785
    ],
    [
      "eJizsGLUFFw",
      0.72,
      0.6825,
      0.6692
    ],
    [
      "eJizsGLUFFw",
      0.73,
      0.6984,
      0.65925
    ],
    [
      "eJizsGLUFFw",
      0.74,
      0.65079999999999993,
      0.65175
    ],
    [
      "eJizsGLUFFw",
      0.75,
      0.6349,
      0.6448
    ],
    [
      "eJizsGLUFFw",
      0.76,
      0.6349,
      0.6403
    ],
    [
      "eJizsGLUFFw",
      0.77,
      0.6349,
      0.63769999999999993
    ],
    [
      "eJizsGLUFFw",
      0.78,
      0.6825,
      0.6315
    ],
    [
      "eJizsGLUFFw",
      0.79,
      0.746,
      0.61444999999999994
    ],
    [
      "eJizsGLUFFw",
      0.8,
      0.66670000000000007,
      0.58475
    ],
    [
      "eJizsGLUFFw",
      0.81,
      0.65079999999999993,
      0.55145
    ],
    [
      "eJizsGLUFFw",
      0.82,
      0.6032,
      0.52965
    ],
    [
      "eJizsGLUFFw",
      0.83,
      0.6349,
      0.52525
    ],
    [
      "eJizsGLUFFw",
      0.84,
      0.6984,
      0.53
    ],
    [
      "eJizsGLUFFw",
      0.85,
      0.65079999999999993,
      0.5339
    ],
    [
      "eJizsGLUFFw",
      0.86,
      0.66670000000000007,
      0.53455
    ],
    [
      "eJizsGLUFFw",
      0.87,
      0.6984,
      0.53225
    ],
    [
      "eJizsGLUFFw",
      0.88,
      0.7302,
      0.5259
    ],
    [
      "eJizsGLUFFw",
      0.89,
      0.6984,
      0.5146
    ],
    [
      "eJizsGLUFFw",
      0.9,
      0.6349,
      0.4976
    ],
    [
      "eJizsGLUFFw",
      0.91,
      0.5079,
      0.47495
    ],
    [
      "eJizsGLUFFw",
      0.92,
      0.4921,
      0.45025
    ],
    [
      "eJizsGLUFFw",
      0.93,
      0.44439999999999996,
      0.43255
    ],
    [
      "eJizsGLUFFw",
      0.94,
      0.44439999999999996,
      0.4316
    ],
    [
      "eJizsGLUFFw",
      0.95,
      0.4286,
      0.44630000000000003
    ],
    [
      "eJizsGLUFFw",
      0.96,
      0.4127,
      0.46575
    ],
    [
      "eJizsGLUFFw",
      0.97,
      0.4286,
      0.4798
    ],
    [
      "eJizsGLUFFw",
      0.98,
      0.3968,
      0.48485
    ],
    [
      "eJizsGLUFFw",
      0.99,
      0.381,
      0.48265
    ],
    [
      "eJizsGLUFFw",
      1,
      0.3016,
      0.478
    ]
  ]
}
